JPSLMenus/__init__.py
JPSLMenus/js/menu.js
JPSLMenus-0.5.0.dist-info/METADATA
JPSLMenus-0.5.0.dist-info/WHEEL
JPSLMenus-0.5.0.dist-info/top_level.txt
JPSLMenus-0.5.0.dist-info/RECORD
