Metadata-Version: 2.1
Name: JPSLMenus
Version: 0.5.0
Summary: Tools to build menus
Home-page: https://github.com/JupyterPhysSciLab/JPSLMenus
Author: Jonathan Gutow
Author-email: gutow@uwosh.edu
License: GPL-3.0+
Classifier: Development Status :: 4 - Beta
Classifier: Intended Audience :: Developers
Classifier: Intended Audience :: Education
Classifier: License :: OSI Approved :: GNU General Public License v3 or later (GPLv3+)
Classifier: Programming Language :: Python :: 3
Classifier: Programming Language :: JavaScript
Classifier: Operating System :: OS Independent
Requires-Dist: jupyter (>=1.0.0)
